pygaia/__init__.py
pygaia/utils.py
pygaia/astrometry/__init__.py
pygaia/astrometry/constants.py
pygaia/astrometry/coordinates.py
pygaia/astrometry/vectorastrometry.py
pygaia/errors/__init__.py
pygaia/errors/astrometric.py
pygaia/errors/photometric.py
pygaia/errors/spectroscopic.py
pygaia/errors/utils.py
pygaia/errors/data/LogErrVsMagSpline2.csv
pygaia/errors/data/rv_uncertainty_model_coeffs.json
pygaia/photometry/__init__.py
pygaia/photometry/transformations.py
pygaia/photometry/utils.py
pygaia/plot/__init__.py
pygaia/plot/sky.py
pygaia/tests/test_coordinates.py
pygaia/tests/test_errors_astrometric.py
pygaia/tests/test_utils.py
pygaia/tests/test_vectorAstrometry.py
pygaia-3.2.2.dist-info/AUTHORS.md
pygaia-3.2.2.dist-info/LICENSE
pygaia-3.2.2.dist-info/METADATA
pygaia-3.2.2.dist-info/WHEEL
pygaia-3.2.2.dist-info/top_level.txt
pygaia-3.2.2.dist-info/RECORD
