Metadata-Version: 2.1
Name: pygaia
Version: 3.2.2
Summary: Gaia science performance simulation toolkit
Author-email: "Anthony G.A. Brown" <brown@strw.leidenuniv.nl>
Project-URL: Homepage, https://github.com/agabrown/PyGaia
Project-URL: Documentation, https://PyGaia.readthedocs.io/en/latest/
Project-URL: Source, https://github.com/agabrown/PyGaia
Project-URL: Bug Tracker, https://github.com/agabrown/PyGaia/issues
Keywords: plotting, data analysis, numerical tools
Classifier: Operating System :: OS Independent
Classifier: Programming Language :: Python :: 3
Classifier: Development Status :: 4 - Beta
Classifier: License :: OSI Approved :: BSD License
Classifier: Topic :: Scientific/Engineering :: Astronomy
Classifier: Intended Audience :: Science/Research
Requires-Python: >=3.6
License-File: LICENSE
License-File: AUTHORS.md
Requires-Dist: numpy>=1.19
Requires-Dist: scipy>=1.7
Requires-Dist: pandas>=1.3
Requires-Dist: matplotlib>=3.0
Requires-Dist: ujson>=5
Requires-Dist: astropy>=5
Provides-Extra: docs
Requires-Dist: sphinx>=4.4.0; extra == "docs"
Requires-Dist: myst-parser>=0.18; extra == "docs"
Requires-Dist: myst-nb>=1.0; extra == "docs"
Requires-Dist: sphinx-book-theme>=0.3.3; extra == "docs"
Requires-Dist: sphinx-automodapi>=0.14; extra == "docs"
